expand/__init__.py
expand-0.2.2.dist-info/LICENSE
expand-0.2.2.dist-info/WHEEL
expand-0.2.2.dist-info/METADATA
expand-0.2.2.dist-info/RECORD
