Metadata-Version: 2.1
Name: expand
Version: 0.2.2
Summary: Expand is a tool to expand out potential versions from a requirements.txt.
Home-page: UNKNOWN
License: UNKNOWN
Author: Marc Brooks
Author-email: marcwbrooks@gmail.com
Classifier: License :: OSI Approved :: MIT License
